[{"id":217353,"term":"202210","termDesc":"2022 Spring Semester","courseReferenceNumber":"10495","partOfTerm":"1","courseNumber":"216","subject":"CSE","subjectDescription":"Computer Science &amp; Engineering","sequenceNumber":"010","campusDescription":"Engineering&amp;App Sci On Campus","scheduleTypeDescription":"Lecture","courseTitle":"Software Engineering","creditHours":null,"maximumEnrollment":35,"enrollment":39,"seatsAvailable":-4,"waitCapacity":0,"waitCount":0,"waitAvailable":0,"crossList":"YX","crossListCapacity":65,"crossListCount":63,"crossListAvailable":2,"creditHourHigh":null,"creditHourLow":3,"creditHourIndicator":null,"openSection":false,"linkIdentifier":null,"isSectionLinked":false,"subjectCourse":"CSE216","faculty":[{"bannerId":"15620","category":null,"class":"net.hedtech.banner.student.faculty.FacultyResultDecorator","courseReferenceNumber":"10495","displayName":"Urban, Stephen","emailAddress":null,"primaryIndicator":true,"term":"202210"}],"meetingsFaculty":[{"category":"01","class":"net.hedtech.banner.student.schedule.SectionSessionDecorator","courseReferenceNumber":"10495","faculty":[],"meetingTime":{"beginTime":"0920","building":"SI","buildingDescription":"000  Sinclair Laboratory","campus":"A","campusDescription":"Asa Packer Campus","category":"01","class":"net.hedtech.banner.general.overall.MeetingTimeDecorator","courseReferenceNumber":"10495","creditHourSession":3,"endDate":"05/06/2022","endTime":"1035","friday":false,"hoursWeek":2.5,"meetingScheduleType":"L","meetingType":"COCO","meetingTypeDescription":"Class On-Campus Only","monday":true,"room":"AUD","saturday":false,"startDate":"01/24/2022","sunday":false,"term":"202210","thursday":false,"tuesday":false,"wednesday":true},"term":"202210"}],"reservedSeatSummary":null,"sectionAttributes":[{"class":"net.hedtech.banner.student.schedule.SectionDegreeProgramAttributeDecorator","code":"CAMP","courseReferenceNumber":"10495","description":"On-Campus Required","isZTCAttribute":false,"termCode":"202210"},{"class":"net.hedtech.banner.student.schedule.SectionDegreeProgramAttributeDecorator","code":"ND","courseReferenceNumber":"10495","description":"Not Designated","isZTCAttribute":false,"termCode":"202210"}],"instructionalMethod":null,"instructionalMethodDescription":null},{"id":218909,"term":"202210","termDesc":"2022 Spring Semester","courseReferenceNumber":"15650","partOfTerm":"1","courseNumber":"216","subject":"CSE","subjectDescription":"Computer Science &amp; Engineering","sequenceNumber":"011","campusDescription":"Engineering&amp;App Sci On Campus","scheduleTypeDescription":"Lecture","courseTitle":"Software Engineering","creditHours":null,"maximumEnrollment":35,"enrollment":24,"seatsAvailable":11,"waitCapacity":0,"waitCount":0,"waitAvailable":0,"crossList":"YX","crossListCapacity":65,"crossListCount":63,"crossListAvailable":2,"creditHourHigh":null,"creditHourLow":3,"creditHourIndicator":null,"openSection":true,"linkIdentifier":null,"isSectionLinked":false,"subjectCourse":"CSE216","faculty":[{"bannerId":"16068","category":null,"class":"net.hedtech.banner.student.faculty.FacultyResultDecorator","courseReferenceNumber":"15650","displayName":"Erle, Mark","emailAddress":null,"primaryIndicator":true,"term":"202210"}],"meetingsFaculty":[{"category":"01","class":"net.hedtech.banner.student.schedule.SectionSessionDecorator","courseReferenceNumber":"15650","faculty":[],"meetingTime":{"beginTime":"0920","building":"SI","buildingDescription":"000  Sinclair Laboratory","campus":"A","campusDescription":"Asa Packer Campus","category":"01","class":"net.hedtech.banner.general.overall.MeetingTimeDecorator","courseReferenceNumber":"15650","creditHourSession":3,"endDate":"05/06/2022","endTime":"1035","friday":false,"hoursWeek":2.5,"meetingScheduleType":"L","meetingType":"COCO","meetingTypeDescription":"Class On-Campus Only","monday":true,"room":"AUD","saturday":false,"startDate":"01/24/2022","sunday":false,"term":"202210","thursday":false,"tuesday":false,"wednesday":true},"term":"202210"}],"reservedSeatSummary":null,"sectionAttributes":[{"class":"net.hedtech.banner.student.schedule.SectionDegreeProgramAttributeDecorator","code":"CAMP","courseReferenceNumber":"15650","description":"On-Campus Required","isZTCAttribute":false,"termCode":"202210"}],"instructionalMethod":null,"instructionalMethodDescription":null}]