[{"id":218273,"term":"202210","termDesc":"2022 Spring Semester","courseReferenceNumber":"13835","partOfTerm":"1","courseNumber":"446","subject":"PHY","subjectDescription":"Physics","sequenceNumber":"010","campusDescription":"Arts &amp; Sciences On Campus","scheduleTypeDescription":"Lecture","courseTitle":"Atomic and Molecular Physics","creditHours":null,"maximumEnrollment":19,"enrollment":6,"seatsAvailable":13,"waitCapacity":5,"waitCount":0,"waitAvailable":5,"crossList":null,"crossListCapacity":null,"crossListCount":null,"crossListAvailable":null,"creditHourHigh":null,"creditHourLow":3,"creditHourIndicator":null,"openSection":true,"linkIdentifier":null,"isSectionLinked":false,"subjectCourse":"PHY446","faculty":[{"bannerId":"8915","category":null,"class":"net.hedtech.banner.student.faculty.FacultyResultDecorator","courseReferenceNumber":"13835","displayName":"Sommer, Ariel","emailAddress":"ats317@lehigh.edu","primaryIndicator":true,"term":"202210"}],"meetingsFaculty":[{"category":"01","class":"net.hedtech.banner.student.schedule.SectionSessionDecorator","courseReferenceNumber":"13835","faculty":[],"meetingTime":{"beginTime":"1625","building":"LL","buildingDescription":"016  Lewis Lab","campus":"A","campusDescription":"Asa Packer Campus","category":"01","class":"net.hedtech.banner.general.overall.MeetingTimeDecorator","courseReferenceNumber":"13835","creditHourSession":3,"endDate":"05/06/2022","endTime":"1740","friday":false,"hoursWeek":2.5,"meetingScheduleType":"L","meetingType":"COCO","meetingTypeDescription":"Class On-Campus Only","monday":true,"room":"512","saturday":false,"startDate":"01/24/2022","sunday":false,"term":"202210","thursday":false,"tuesday":false,"wednesday":true},"term":"202210"}],"reservedSeatSummary":null,"sectionAttributes":[{"class":"net.hedtech.banner.student.schedule.SectionDegreeProgramAttributeDecorator","code":"CAMP","courseReferenceNumber":"13835","description":"On-Campus Required","isZTCAttribute":false,"termCode":"202210"},{"class":"net.hedtech.banner.student.schedule.SectionDegreeProgramAttributeDecorator","code":"NS","courseReferenceNumber":"13835","description":"Natural Science Requirement","isZTCAttribute":false,"termCode":"202210"}],"instructionalMethod":null,"instructionalMethodDescription":null}]